Metadata-Version: 2.1
Name: algosto
Version: 0.0.18
Summary: Algosto implements stochastic algorithms.
Home-page: https://github.com/Melvin-klein/algosto
Author: Melvine Nargeot
Author-email: Melvine Nargeot <melvine.nargeot@gmail.com>
Requires-Python: >=3.7
Requires-Dist: matplotlib>=2.25.1
Requires-Dist: numpy>=1.19.5
